[
  {
    "id": 1,
    "uuid": "ST2025-000001",
    "firstName": "John",
    "lastName": "Doe",
    "email": "john.doe@example.com",
    "phone": "+491234567890",
    "nationality": "Indian",
    "dateOfBirth": "2000-05-15",
    "gender": "Male",
    "targetCountries": ["Germany", "UK"],
    "targetIntake": "Winter 2025/26",
    "educationLevel": "Bachelor",
    "fieldOfStudy": "Computer Science",
    "gpa": 3.6,
    "englishProficiency": "IELTS 7.0",
    "status": "ACTIVE",
    "registrationDate": "2025-01-10T08:30:00Z",
    "profileProgress": 75,
    "assignedAdminId": 3,
    "isFirstLogin": false,
    "emailVerified": true,
    "phoneVerified": true
  },
  {
    "id": 2,
    "uuid": "ST2025-000002",
    "firstName": "Priya",
    "lastName": "Sharma",
    "email": "priya.sharma@example.com",
    "phone": "+919876543210",
    "nationality": "Indian",
    "dateOfBirth": "2001-08-22",
    "gender": "Female",
    "targetCountries": ["Germany"],
    "targetIntake": "Summer 2025",
    "educationLevel": "Bachelor",
    "fieldOfStudy": "Mechanical Engineering",
    "gpa": 3.8,
    "englishProficiency": "TOEFL 105",
    "status": "ACTIVE",
    "registrationDate": "2025-02-15T10:00:00Z",
    "profileProgress": 90,
    "assignedAdminId": 3,
    "isFirstLogin": false,
    "emailVerified": true,
    "phoneVerified": true
  },
  {
    "id": 3,
    "uuid": "ST2025-000003",
    "firstName": "Ahmed",
    "lastName": "Khan",
    "email": "ahmed.khan@example.com",
    "phone": "+971501234567",
    "nationality": "Pakistani",
    "dateOfBirth": "1999-11-03",
    "gender": "Male",
    "targetCountries": ["UK"],
    "targetIntake": "Fall 2025",
    "educationLevel": "Master",
    "fieldOfStudy": "Data Science",
    "gpa": 3.4,
    "englishProficiency": "IELTS 7.5",
    "status": "ACTIVE",
    "registrationDate": "2025-03-01T14:00:00Z",
    "profileProgress": 45,
    "assignedAdminId": 4,
    "isFirstLogin": true,
    "emailVerified": true,
    "phoneVerified": false
  },
  {
    "id": 4,
    "uuid": "ST2025-000004",
    "firstName": "Maria",
    "lastName": "Garcia",
    "email": "maria.garcia@example.com",
    "phone": "+34612345678",
    "nationality": "Spanish",
    "dateOfBirth": "2000-03-18",
    "gender": "Female",
    "targetCountries": ["Germany", "Italy"],
    "targetIntake": "Winter 2025/26",
    "educationLevel": "Master",
    "fieldOfStudy": "MBA",
    "gpa": 3.9,
    "englishProficiency": "TOEFL 110",
    "status": "ACTIVE",
    "registrationDate": "2025-01-20T09:00:00Z",
    "profileProgress": 60,
    "assignedAdminId": 5,
    "isFirstLogin": false,
    "emailVerified": true,
    "phoneVerified": true
  },
  {
    "id": 5,
    "uuid": "ST2025-000005",
    "firstName": "Wei",
    "lastName": "Zhang",
    "email": "wei.zhang@example.com",
    "phone": "+8613800138000",
    "nationality": "Chinese",
    "dateOfBirth": "2001-07-07",
    "gender": "Male",
    "targetCountries": ["UK", "Germany"],
    "targetIntake": "Fall 2025",
    "educationLevel": "Bachelor",
    "fieldOfStudy": "Electrical Engineering",
    "gpa": 3.7,
    "englishProficiency": "IELTS 7.0",
    "status": "ACTIVE",
    "registrationDate": "2025-02-28T11:00:00Z",
    "profileProgress": 30,
    "assignedAdminId": 3,
    "isFirstLogin": false,
    "emailVerified": true,
    "phoneVerified": true
  }
]
